{
  "list.insertMappings": {
    "<C-n>": "<Down>",
    "<C-p>": "<Up>"
  },
  "suggest.noselect": false,
  "snippets.ultisnips.directories": ["UltiSnips", "~/.config/nvim/snippets"],
  "emmet.includeLanguages": {
    "javascript": "javascriptreact",
    "typescript": "typescriptreact"
  },
  "html.autoClosingTags": true,
  "snippets.extends": {
    "javascriptreact": ["javascript"],
    "typescriptreact": ["javascript"],
    "typescript": ["javascript"]
  },
  "coc.preferences.formatOnSaveFiletypes": [
    "css",
    "markdown",
    "html",
    "javascript",
    "typescript",
    "typescriptreact",
    "json",
    "javascriptreact",
    "typescript.tsx",
    "graphql"
  ],
  "tsserver.formatOnType": true,
  "coc.preferences.formatOnType": true
}
